{"_objective": {"is_multi_objective": false, "metrics": [{"_class_path": "fedot.core.composer.metrics/QualityMetric.get_value"}, {"value": "node_number", "_class_path": "fedot.core.repository.quality_metrics_repository/ComplexityMetricsEnum"}], "_class_path": "fedot.core.optimisers.objective.objective/Objective"}, "archive_history": [["0c821891-a700-488d-b230-e78e10493347"], ["05266d98-4a26-4d30-ba98-2a8773ddf789"]], "individuals": [["0c821891-a700-488d-b230-e78e10493347"], ["d297c913-f81c-4e45-a6d4-6af9c1a1d832", "611430d0-9d63-4067-bdce-4b128cc7541b", "5b5a8c11-9cdd-4303-a35b-8093fc4ba429", "2bdb0618-79bc-4c21-aec1-291cffa6c72e", "d6678845-c769-43ff-bc57-4f51f4341949", "56909b23-5b25-44ac-80c6-d174a25353f6", "142d656d-0bae-432d-855c-2a30a611429c", "3e679620-c0a5-4e26-879a-c3672ad81dca", "ba991f2b-b1aa-4867-a699-67ec47691de8", "d83f62eb-a1e4-47c0-8ed2-0bcf38783558", "8c55fa42-3fbd-4013-8109-db85235bb9a5", "05266d98-4a26-4d30-ba98-2a8773ddf789", "94078775-efc3-44e2-9927-1904df9c9a64", "e008a2c4-f338-468a-b7c4-41fa27df6615", "0c821891-a700-488d-b230-e78e10493347"]], "_class_path": "fedot.core.optimisers.opt_history_objects.opt_history/OptHistory", "individuals_pool": [{"fitness": {"_values": [0.17699145640084318, 0.2], "_class_path": "fedot.core.optimisers.fitness.fitness/SingleObjFitness"}, "graph": {"operator": {"_nodes": [{"_nodes_from": ["105e20d4-52f2-4fb9-bef3-f26f1db9e9c9"], "content": {"name": "rf", "params": {"n_jobs": 1}, "metadata": {"metric": null, "_class_path": "fedot.core.pipelines.node/NodeMetadata"}}, "uid": "90ece3ee-4e51-4c9c-b730-c2b50d4cd011", "_class_path": "fedot.core.dag.linked_graph_node/LinkedGraphNode"}, {"_nodes_from": [], "content": {"name": "scaling", "params": {}, "metadata": {"metric": null, "_class_path": "fedot.core.pipelines.node/NodeMetadata"}}, "uid": "105e20d4-52f2-4fb9-bef3-f26f1db9e9c9", "_class_path": "fedot.core.dag.linked_graph_node/LinkedGraphNode"}], "_postprocess_nodes": {"_class_path": "fedot.core.dag.linked_graph/LinkedGraph._empty_postprocess"}, "_class_path": "fedot.core.dag.linked_graph/LinkedGraph"}, "_class_path": "fedot.core.dag.graph_delegate/GraphDelegate"}, "metadata": {"computation_time_in_seconds": 600.9620309248567, "evaluation_time_iso": "2022-11-02T18:33:14.561342"}, "native_generation": 0, "parent_operator": null, "uid": "0c821891-a700-488d-b230-e78e10493347", "_class_path": "fedot.core.optimisers.opt_history_objects.individual/Individual"}, {"fitness": {"_values": [0.22896128607488692, 0.2], "_class_path": "fedot.core.optimisers.fitness.fitness/SingleObjFitness"}, "graph": {"operator": {"_nodes": [{"_nodes_from": ["651d54a3-5330-4116-9950-2dda2f047967"], "content": {"name": "rf", "params": {"n_jobs": 1, "n_estimators": 100, "criterion": "gini", "max_features": 0.16159148376205507, "min_samples_split": 2, "min_samples_leaf": 8, "bootstrap": false}, "metadata": {"metric": null, "_class_path": "fedot.core.pipelines.node/NodeMetadata"}}, "uid": "1d180f01-f2a1-4938-a7a5-5c9546591ae4", "_class_path": "fedot.core.dag.linked_graph_node/LinkedGraphNode"}, {"_nodes_from": [], "content": {"name": "scaling", "params": {}, "metadata": {"metric": null, "_class_path": "fedot.core.pipelines.node/NodeMetadata"}}, "uid": "651d54a3-5330-4116-9950-2dda2f047967", "_class_path": "fedot.core.dag.linked_graph_node/LinkedGraphNode"}], "_postprocess_nodes": {"_class_path": "fedot.core.dag.linked_graph/LinkedGraph._empty_postprocess"}, "_class_path": "fedot.core.dag.linked_graph/LinkedGraph"}, "_class_path": "fedot.core.dag.graph_delegate/GraphDelegate"}, "metadata": {"computation_time_in_seconds": 847.5747902356088, "evaluation_time_iso": "2022-11-02T18:47:22.889092"}, "native_generation": 1, "parent_operator": {"operators": ["<function parameter_change_mutation at 0x7fe423f6b9d0>"], "parent_individuals": ["0c821891-a700-488d-b230-e78e10493347"], "type_": "mutation", "uid": "f0ae9188-25da-4ecb-a57e-9c5d0d17900c", "_class_path": "fedot.core.optimisers.opt_history_objects.parent_operator/ParentOperator"}, "uid": "d297c913-f81c-4e45-a6d4-6af9c1a1d832", "_class_path": "fedot.core.optimisers.opt_history_objects.individual/Individual"}, {"fitness": {"_values": [1.8840309949022411, 0.3], "_class_path": "fedot.core.optimisers.fitness.fitness/SingleObjFitness"}, "graph": {"operator": {"_nodes": [{"_nodes_from": ["2c56e076-60c9-4752-8722-9b9dadb2f3ee"], "content": {"name": "rf", "params": {"n_jobs": 1}, "metadata": {"metric": null, "_class_path": "fedot.core.pipelines.node/NodeMetadata"}}, "uid": "1033dec4-25c8-4a9f-a32e-14b8794acc15", "_class_path": "fedot.core.dag.linked_graph_node/LinkedGraphNode"}, {"_nodes_from": [], "content": {"name": "scaling", "params": {}, "metadata": {"metric": null, "_class_path": "fedot.core.pipelines.node/NodeMetadata"}}, "uid": "2c56e076-60c9-4752-8722-9b9dadb2f3ee", "_class_path": "fedot.core.dag.linked_graph_node/LinkedGraphNode"}, {"_nodes_from": ["1033dec4-25c8-4a9f-a32e-14b8794acc15"], "content": {"name": "qda", "params": {}, "metadata": {"metric": null, "_class_path": "fedot.core.pipelines.node/NodeMetadata"}}, "uid": "6f04027b-e6db-4ed8-a123-25750e44f721", "_class_path": "fedot.core.dag.linked_graph_node/LinkedGraphNode"}], "_postprocess_nodes": {"_class_path": "fedot.core.dag.linked_graph/LinkedGraph._empty_postprocess"}, "_class_path": "fedot.core.dag.linked_graph/LinkedGraph"}, "_class_path": "fedot.core.dag.graph_delegate/GraphDelegate"}, "metadata": {"computation_time_in_seconds": 137.69151045009494, "evaluation_time_iso": "2022-11-02T18:49:40.580818"}, "native_generation": 1, "parent_operator": {"operators": ["MutationTypesEnum.single_add"], "parent_individuals": ["0c821891-a700-488d-b230-e78e10493347"], "type_": "mutation", "uid": "8d654f6a-c728-4ac5-a574-33f6a7c8e6ec", "_class_path": "fedot.core.optimisers.opt_history_objects.parent_operator/ParentOperator"}, "uid": "611430d0-9d63-4067-bdce-4b128cc7541b", "_class_path": "fedot.core.optimisers.opt_history_objects.individual/Individual"}, {"fitness": {"_values": [1.9002339140431803, 0.3], "_class_path": "fedot.core.optimisers.fitness.fitness/SingleObjFitness"}, "graph": {"operator": {"_nodes": [{"_nodes_from": ["6983b82e-6487-4265-88b2-89389319f323"], "content": {"name": "rf", "params": {"n_jobs": 1}, "metadata": {"metric": null, "_class_path": "fedot.core.pipelines.node/NodeMetadata"}}, "uid": "aabaeb45-a137-4a8b-9ad1-47f1c92080b7", "_class_path": "fedot.core.dag.linked_graph_node/LinkedGraphNode"}, {"_nodes_from": ["b976a008-c8f2-43e7-8095-d2947bfdda07"], "content": {"name": "scaling", "params": {}, "metadata": {"metric": null, "_class_path": "fedot.core.pipelines.node/NodeMetadata"}}, "uid": "6983b82e-6487-4265-88b2-89389319f323", "_class_path": "fedot.core.dag.linked_graph_node/LinkedGraphNode"}, {"_nodes_from": [], "content": {"name": "pca", "params": {"svd_solver": "full", "n_components": 0.7}, "metadata": {"metric": null, "_class_path": "fedot.core.pipelines.node/NodeMetadata"}}, "uid": "b976a008-c8f2-43e7-8095-d2947bfdda07", "_class_path": "fedot.core.dag.linked_graph_node/LinkedGraphNode"}], "_postprocess_nodes": {"_class_path": "fedot.core.dag.linked_graph/LinkedGraph._empty_postprocess"}, "_class_path": "fedot.core.dag.linked_graph/LinkedGraph"}, "_class_path": "fedot.core.dag.graph_delegate/GraphDelegate"}, "metadata": {"computation_time_in_seconds": 625.9145029634237, "evaluation_time_iso": "2022-11-02T19:00:06.495524"}, "native_generation": 1, "parent_operator": {"operators": ["MutationTypesEnum.single_add"], "parent_individuals": ["0c821891-a700-488d-b230-e78e10493347"], "type_": "mutation", "uid": "a1c3e0e5-409a-4eca-a958-a48bcf5239c3", "_class_path": "fedot.core.optimisers.opt_history_objects.parent_operator/ParentOperator"}, "uid": "5b5a8c11-9cdd-4303-a35b-8093fc4ba429", "_class_path": "fedot.core.optimisers.opt_history_objects.individual/Individual"}, {"fitness": {"_values": [0.18141298282840465, 0.2], "_class_path": "fedot.core.optimisers.fitness.fitness/SingleObjFitness"}, "graph": {"operator": {"_nodes": [{"_nodes_from": ["aa4d9c9a-bb39-496d-adbf-a95d827dd4fb"], "content": {"name": "rf", "params": {"n_jobs": 1, "n_estimators": 100, "criterion": "gini", "max_features": 0.817998914625271, "min_samples_split": 6, "min_samples_leaf": 12, "bootstrap": true}, "metadata": {"metric": null, "_class_path": "fedot.core.pipelines.node/NodeMetadata"}}, "uid": "80ef1878-5609-4de3-abf6-9e76d9303fb2", "_class_path": "fedot.core.dag.linked_graph_node/LinkedGraphNode"}, {"_nodes_from": [], "content": {"name": "scaling", "params": {}, "metadata": {"metric": null, "_class_path": "fedot.core.pipelines.node/NodeMetadata"}}, "uid": "aa4d9c9a-bb39-496d-adbf-a95d827dd4fb", "_class_path": "fedot.core.dag.linked_graph_node/LinkedGraphNode"}], "_postprocess_nodes": {"_class_path": "fedot.core.dag.linked_graph/LinkedGraph._empty_postprocess"}, "_class_path": "fedot.core.dag.linked_graph/LinkedGraph"}, "_class_path": "fedot.core.dag.graph_delegate/GraphDelegate"}, "metadata": {"computation_time_in_seconds": 1825.762940146029, "evaluation_time_iso": "2022-11-02T19:30:32.258692"}, "native_generation": 1, "parent_operator": {"operators": ["<function parameter_change_mutation at 0x7fe423f6b9d0>"], "parent_individuals": ["0c821891-a700-488d-b230-e78e10493347"], "type_": "mutation", "uid": "10719d52-5f5c-4603-92d1-8192563357ac", "_class_path": "fedot.core.optimisers.opt_history_objects.parent_operator/ParentOperator"}, "uid": "2bdb0618-79bc-4c21-aec1-291cffa6c72e", "_class_path": "fedot.core.optimisers.opt_history_objects.individual/Individual"}, {"fitness": {"_values": [31.30592348690514, 0.2], "_class_path": "fedot.core.optimisers.fitness.fitness/SingleObjFitness"}, "graph": {"operator": {"_nodes": [{"_nodes_from": ["ac8d1fbd-d021-469b-b49f-8637c09039e4"], "content": {"name": "qda", "params": {}, "metadata": {"metric": null, "_class_path": "fedot.core.pipelines.node/NodeMetadata"}}, "uid": "aab112ed-5f22-46b2-b10a-12435e401bd3", "_class_path": "fedot.core.dag.linked_graph_node/LinkedGraphNode"}, {"_nodes_from": [], "content": {"name": "scaling", "params": {}, "metadata": {"metric": null, "_class_path": "fedot.core.pipelines.node/NodeMetadata"}}, "uid": "ac8d1fbd-d021-469b-b49f-8637c09039e4", "_class_path": "fedot.core.dag.linked_graph_node/LinkedGraphNode"}], "_postprocess_nodes": {"_class_path": "fedot.core.dag.linked_graph/LinkedGraph._empty_postprocess"}, "_class_path": "fedot.core.dag.linked_graph/LinkedGraph"}, "_class_path": "fedot.core.dag.graph_delegate/GraphDelegate"}, "metadata": {"computation_time_in_seconds": 38.55013162270188, "evaluation_time_iso": "2022-11-02T19:31:10.809011"}, "native_generation": 1, "parent_operator": {"operators": ["MutationTypesEnum.single_change"], "parent_individuals": ["0c821891-a700-488d-b230-e78e10493347"], "type_": "mutation", "uid": "4942bb19-c3b6-4f39-858c-857b90532ca9", "_class_path": "fedot.core.optimisers.opt_history_objects.parent_operator/ParentOperator"}, "uid": "d6678845-c769-43ff-bc57-4f51f4341949", "_class_path": "fedot.core.optimisers.opt_history_objects.individual/Individual"}, {"fitness": {"_values": [0.177012382384237, 0.3], "_class_path": "fedot.core.optimisers.fitness.fitness/SingleObjFitness"}, "graph": {"operator": {"_nodes": [{"_nodes_from": ["f736b765-a68f-4f46-b2d1-c7afecec5d66"], "content": {"name": "rf", "params": {"n_jobs": 1}, "metadata": {"metric": null, "_class_path": "fedot.core.pipelines.node/NodeMetadata"}}, "uid": "6bff8440-3fbe-4a73-a13f-4c7b38579f93", "_class_path": "fedot.core.dag.linked_graph_node/LinkedGraphNode"}, {"_nodes_from": ["10724dd0-9462-4af8-94ff-0feed93b027a"], "content": {"name": "normalization", "params": {}, "metadata": {"metric": null, "_class_path": "fedot.core.pipelines.node/NodeMetadata"}}, "uid": "f736b765-a68f-4f46-b2d1-c7afecec5d66", "_class_path": "fedot.core.dag.linked_graph_node/LinkedGraphNode"}, {"_nodes_from": [], "content": {"name": "scaling", "params": {}, "metadata": {"metric": null, "_class_path": "fedot.core.pipelines.node/NodeMetadata"}}, "uid": "10724dd0-9462-4af8-94ff-0feed93b027a", "_class_path": "fedot.core.dag.linked_graph_node/LinkedGraphNode"}], "_postprocess_nodes": {"_class_path": "fedot.core.dag.linked_graph/LinkedGraph._empty_postprocess"}, "_class_path": "fedot.core.dag.linked_graph/LinkedGraph"}, "_class_path": "fedot.core.dag.graph_delegate/GraphDelegate"}, "metadata": {"computation_time_in_seconds": 619.6082546636462, "evaluation_time_iso": "2022-11-02T19:41:30.417453"}, "native_generation": 1, "parent_operator": {"operators": ["MutationTypesEnum.single_add"], "parent_individuals": ["0c821891-a700-488d-b230-e78e10493347"], "type_": "mutation", "uid": "0742e4b9-d79f-4424-8434-996f042004fb", "_class_path": "fedot.core.optimisers.opt_history_objects.parent_operator/ParentOperator"}, "uid": "56909b23-5b25-44ac-80c6-d174a25353f6", "_class_path": "fedot.core.optimisers.opt_history_objects.individual/Individual"}, {"fitness": {"_values": [31.5808600401047, 0.3], "_class_path": "fedot.core.optimisers.fitness.fitness/SingleObjFitness"}, "graph": {"operator": {"_nodes": [{"_nodes_from": ["3e91ae0e-9432-4133-b858-65dbdf739087"], "content": {"name": "qda", "params": {}, "metadata": {"metric": null, "_class_path": "fedot.core.pipelines.node/NodeMetadata"}}, "uid": "91f6bbb6-e210-441e-b598-2093aeb3ce24", "_class_path": "fedot.core.dag.linked_graph_node/LinkedGraphNode"}, {"_nodes_from": ["21d6310b-2777-416d-9a39-82a11c26b4e3"], "content": {"name": "normalization", "params": {}, "metadata": {"metric": null, "_class_path": "fedot.core.pipelines.node/NodeMetadata"}}, "uid": "3e91ae0e-9432-4133-b858-65dbdf739087", "_class_path": "fedot.core.dag.linked_graph_node/LinkedGraphNode"}, {"_nodes_from": [], "content": {"name": "scaling", "params": {}, "metadata": {"metric": null, "_class_path": "fedot.core.pipelines.node/NodeMetadata"}}, "uid": "21d6310b-2777-416d-9a39-82a11c26b4e3", "_class_path": "fedot.core.dag.linked_graph_node/LinkedGraphNode"}], "_postprocess_nodes": {"_class_path": "fedot.core.dag.linked_graph/LinkedGraph._empty_postprocess"}, "_class_path": "fedot.core.dag.linked_graph/LinkedGraph"}, "_class_path": "fedot.core.dag.graph_delegate/GraphDelegate"}, "metadata": {"computation_time_in_seconds": 40.89477092400193, "evaluation_time_iso": "2022-11-02T19:42:11.312422"}, "native_generation": 1, "parent_operator": {"operators": ["MutationTypesEnum.single_change", "MutationTypesEnum.single_add"], "parent_individuals": ["0c821891-a700-488d-b230-e78e10493347"], "type_": "mutation", "uid": "edae0a74-1a59-47ee-90f1-59fd32f1be8b", "_class_path": "fedot.core.optimisers.opt_history_objects.parent_operator/ParentOperator"}, "uid": "142d656d-0bae-432d-855c-2a30a611429c", "_class_path": "fedot.core.optimisers.opt_history_objects.individual/Individual"}, {"fitness": {"_values": [1.9035632610676145, 0.2], "_class_path": "fedot.core.optimisers.fitness.fitness/SingleObjFitness"}, "graph": {"operator": {"_nodes": [{"_nodes_from": ["9b35da53-8c0c-45a2-acdf-2cc44e096b48"], "content": {"name": "rf", "params": {"n_jobs": 1}, "metadata": {"metric": null, "_class_path": "fedot.core.pipelines.node/NodeMetadata"}}, "uid": "d0d10aa2-b909-44b9-931a-614c02129a65", "_class_path": "fedot.core.dag.linked_graph_node/LinkedGraphNode"}, {"_nodes_from": [], "content": {"name": "pca", "params": {"svd_solver": "full", "n_components": 0.7}, "metadata": {"metric": null, "_class_path": "fedot.core.pipelines.node/NodeMetadata"}}, "uid": "9b35da53-8c0c-45a2-acdf-2cc44e096b48", "_class_path": "fedot.core.dag.linked_graph_node/LinkedGraphNode"}], "_postprocess_nodes": {"_class_path": "fedot.core.dag.linked_graph/LinkedGraph._empty_postprocess"}, "_class_path": "fedot.core.dag.linked_graph/LinkedGraph"}, "_class_path": "fedot.core.dag.graph_delegate/GraphDelegate"}, "metadata": {"computation_time_in_seconds": 632.7648872472346, "evaluation_time_iso": "2022-11-02T19:52:44.077495"}, "native_generation": 1, "parent_operator": {"operators": ["MutationTypesEnum.single_change"], "parent_individuals": ["0c821891-a700-488d-b230-e78e10493347"], "type_": "mutation", "uid": "8a483e74-fee7-4d19-b4a7-a378094a1b0e", "_class_path": "fedot.core.optimisers.opt_history_objects.parent_operator/ParentOperator"}, "uid": "3e679620-c0a5-4e26-879a-c3672ad81dca", "_class_path": "fedot.core.optimisers.opt_history_objects.individual/Individual"}, {"fitness": {"_values": [0.22740177425250283, 0.2], "_class_path": "fedot.core.optimisers.fitness.fitness/SingleObjFitness"}, "graph": {"operator": {"_nodes": [{"_nodes_from": ["f5c1df5b-0ca4-4183-81b1-60dd475e6502"], "content": {"name": "rf", "params": {"n_jobs": 1, "n_estimators": 100, "criterion": "gini", "max_features": 0.14334487649354274, "min_samples_split": 10, "min_samples_leaf": 6, "bootstrap": false}, "metadata": {"metric": null, "_class_path": "fedot.core.pipelines.node/NodeMetadata"}}, "uid": "50d1faec-5ce2-40e7-ac02-e66ca53dbc48", "_class_path": "fedot.core.dag.linked_graph_node/LinkedGraphNode"}, {"_nodes_from": [], "content": {"name": "scaling", "params": {}, "metadata": {"metric": null, "_class_path": "fedot.core.pipelines.node/NodeMetadata"}}, "uid": "f5c1df5b-0ca4-4183-81b1-60dd475e6502", "_class_path": "fedot.core.dag.linked_graph_node/LinkedGraphNode"}], "_postprocess_nodes": {"_class_path": "fedot.core.dag.linked_graph/LinkedGraph._empty_postprocess"}, "_class_path": "fedot.core.dag.linked_graph/LinkedGraph"}, "_class_path": "fedot.core.dag.graph_delegate/GraphDelegate"}, "metadata": {"computation_time_in_seconds": 808.7868981808424, "evaluation_time_iso": "2022-11-02T20:06:12.864631"}, "native_generation": 1, "parent_operator": {"operators": ["<function parameter_change_mutation at 0x7fe423f6b9d0>"], "parent_individuals": ["0c821891-a700-488d-b230-e78e10493347"], "type_": "mutation", "uid": "e04ba033-9b56-42d9-9778-b11bfa1838ea", "_class_path": "fedot.core.optimisers.opt_history_objects.parent_operator/ParentOperator"}, "uid": "ba991f2b-b1aa-4867-a699-67ec47691de8", "_class_path": "fedot.core.optimisers.opt_history_objects.individual/Individual"}, {"fitness": {"_values": [0.5903666121514763, 0.3], "_class_path": "fedot.core.optimisers.fitness.fitness/SingleObjFitness"}, "graph": {"operator": {"_nodes": [{"_nodes_from": ["95cc1507-2e62-4016-82f3-07054fc1da27"], "content": {"name": "rf", "params": {"n_jobs": 1}, "metadata": {"metric": null, "_class_path": "fedot.core.pipelines.node/NodeMetadata"}}, "uid": "d235c279-c3d7-4a3b-b965-6a8ca760bf03", "_class_path": "fedot.core.dag.linked_graph_node/LinkedGraphNode"}, {"_nodes_from": ["097a453e-3cee-4f68-9e97-114db28f96bb"], "content": {"name": "bernb", "params": {}, "metadata": {"metric": null, "_class_path": "fedot.core.pipelines.node/NodeMetadata"}}, "uid": "95cc1507-2e62-4016-82f3-07054fc1da27", "_class_path": "fedot.core.dag.linked_graph_node/LinkedGraphNode"}, {"_nodes_from": [], "content": {"name": "scaling", "params": {}, "metadata": {"metric": null, "_class_path": "fedot.core.pipelines.node/NodeMetadata"}}, "uid": "097a453e-3cee-4f68-9e97-114db28f96bb", "_class_path": "fedot.core.dag.linked_graph_node/LinkedGraphNode"}], "_postprocess_nodes": {"_class_path": "fedot.core.dag.linked_graph/LinkedGraph._empty_postprocess"}, "_class_path": "fedot.core.dag.linked_graph/LinkedGraph"}, "_class_path": "fedot.core.dag.graph_delegate/GraphDelegate"}, "metadata": {"computation_time_in_seconds": 286.64121801406145, "evaluation_time_iso": "2022-11-02T20:10:59.506041"}, "native_generation": 1, "parent_operator": {"operators": ["MutationTypesEnum.single_add", "MutationTypesEnum.single_add"], "parent_individuals": ["0c821891-a700-488d-b230-e78e10493347"], "type_": "mutation", "uid": "e139b53b-32ed-4906-8b7c-e4826af81953", "_class_path": "fedot.core.optimisers.opt_history_objects.parent_operator/ParentOperator"}, "uid": "d83f62eb-a1e4-47c0-8ed2-0bcf38783558", "_class_path": "fedot.core.optimisers.opt_history_objects.individual/Individual"}, {"fitness": {"_values": [0.631004064359557, 0.2], "_class_path": "fedot.core.optimisers.fitness.fitness/SingleObjFitness"}, "graph": {"operator": {"_nodes": [{"_nodes_from": ["da43be57-9f9c-476c-b51f-4bb76bc0e2de"], "content": {"name": "logit", "params": {}, "metadata": {"metric": null, "_class_path": "fedot.core.pipelines.node/NodeMetadata"}}, "uid": "a3de604f-d9b9-4977-ae18-296d0f1fb855", "_class_path": "fedot.core.dag.linked_graph_node/LinkedGraphNode"}, {"_nodes_from": [], "content": {"name": "scaling", "params": {}, "metadata": {"metric": null, "_class_path": "fedot.core.pipelines.node/NodeMetadata"}}, "uid": "da43be57-9f9c-476c-b51f-4bb76bc0e2de", "_class_path": "fedot.core.dag.linked_graph_node/LinkedGraphNode"}], "_postprocess_nodes": {"_class_path": "fedot.core.dag.linked_graph/LinkedGraph._empty_postprocess"}, "_class_path": "fedot.core.dag.linked_graph/LinkedGraph"}, "_class_path": "fedot.core.dag.graph_delegate/GraphDelegate"}, "metadata": {"computation_time_in_seconds": 116.33323511108756, "evaluation_time_iso": "2022-11-02T20:12:55.839474"}, "native_generation": 1, "parent_operator": {"operators": ["MutationTypesEnum.single_change"], "parent_individuals": ["0c821891-a700-488d-b230-e78e10493347"], "type_": "mutation", "uid": "1a1a174a-d649-4a98-b50a-ceefd28d7322", "_class_path": "fedot.core.optimisers.opt_history_objects.parent_operator/ParentOperator"}, "uid": "8c55fa42-3fbd-4013-8109-db85235bb9a5", "_class_path": "fedot.core.optimisers.opt_history_objects.individual/Individual"}, {"fitness": {"_values": [0.13465145706139067, 0.4], "_class_path": "fedot.core.optimisers.fitness.fitness/SingleObjFitness"}, "graph": {"operator": {"_nodes": [{"_nodes_from": ["bddd7c34-490a-4257-b078-db71a5efb772"], "content": {"name": "rf", "params": {"n_jobs": 1}, "metadata": {"metric": null, "_class_path": "fedot.core.pipelines.node/NodeMetadata"}}, "uid": "2100e63f-26eb-4a5f-bd63-8494d2d47cf5", "_class_path": "fedot.core.dag.linked_graph_node/LinkedGraphNode"}, {"_nodes_from": ["e818dcc7-9abb-4cbe-829f-6da65b39de87", "bce37100-3740-43bd-9636-bcd8be83badc"], "content": {"name": "scaling", "params": {}, "metadata": {"metric": null, "_class_path": "fedot.core.pipelines.node/NodeMetadata"}}, "uid": "bddd7c34-490a-4257-b078-db71a5efb772", "_class_path": "fedot.core.dag.linked_graph_node/LinkedGraphNode"}, {"_nodes_from": [], "content": {"name": "normalization", "params": {}, "metadata": {"metric": null, "_class_path": "fedot.core.pipelines.node/NodeMetadata"}}, "uid": "e818dcc7-9abb-4cbe-829f-6da65b39de87", "_class_path": "fedot.core.dag.linked_graph_node/LinkedGraphNode"}, {"_nodes_from": [], "content": {"name": "pca", "params": {"svd_solver": "full", "n_components": 0.7}, "metadata": {"metric": null, "_class_path": "fedot.core.pipelines.node/NodeMetadata"}}, "uid": "bce37100-3740-43bd-9636-bcd8be83badc", "_class_path": "fedot.core.dag.linked_graph_node/LinkedGraphNode"}], "_postprocess_nodes": {"_class_path": "fedot.core.dag.linked_graph/LinkedGraph._empty_postprocess"}, "_class_path": "fedot.core.dag.linked_graph/LinkedGraph"}, "_class_path": "fedot.core.dag.graph_delegate/GraphDelegate"}, "metadata": {"computation_time_in_seconds": 684.3873289301991, "evaluation_time_iso": "2022-11-02T20:24:20.226992"}, "native_generation": 1, "parent_operator": {"operators": ["MutationTypesEnum.single_add"], "parent_individuals": ["0c821891-a700-488d-b230-e78e10493347"], "type_": "mutation", "uid": "181cdc46-0de0-4924-be15-0e9762b79ae0", "_class_path": "fedot.core.optimisers.opt_history_objects.parent_operator/ParentOperator"}, "uid": "05266d98-4a26-4d30-ba98-2a8773ddf789", "_class_path": "fedot.core.optimisers.opt_history_objects.individual/Individual"}, {"fitness": {"_values": [0.4900954957668386, 0.3], "_class_path": "fedot.core.optimisers.fitness.fitness/SingleObjFitness"}, "graph": {"operator": {"_nodes": [{"_nodes_from": ["9f9d1ccf-66ac-4318-9389-d4270316547a"], "content": {"name": "rf", "params": {"n_jobs": 1}, "metadata": {"metric": null, "_class_path": "fedot.core.pipelines.node/NodeMetadata"}}, "uid": "15f94040-6e4d-46df-a6c7-55d9785f9fc7", "_class_path": "fedot.core.dag.linked_graph_node/LinkedGraphNode"}, {"_nodes_from": ["9d685405-934f-42a6-b323-0a36ce228281"], "content": {"name": "pca", "params": {"svd_solver": "full", "n_components": 0.7}, "metadata": {"metric": null, "_class_path": "fedot.core.pipelines.node/NodeMetadata"}}, "uid": "9f9d1ccf-66ac-4318-9389-d4270316547a", "_class_path": "fedot.core.dag.linked_graph_node/LinkedGraphNode"}, {"_nodes_from": [], "content": {"name": "scaling", "params": {}, "metadata": {"metric": null, "_class_path": "fedot.core.pipelines.node/NodeMetadata"}}, "uid": "9d685405-934f-42a6-b323-0a36ce228281", "_class_path": "fedot.core.dag.linked_graph_node/LinkedGraphNode"}], "_postprocess_nodes": {"_class_path": "fedot.core.dag.linked_graph/LinkedGraph._empty_postprocess"}, "_class_path": "fedot.core.dag.linked_graph/LinkedGraph"}, "_class_path": "fedot.core.dag.graph_delegate/GraphDelegate"}, "metadata": {"computation_time_in_seconds": 825.2526506409049, "evaluation_time_iso": "2022-11-02T20:38:05.479823"}, "native_generation": 1, "parent_operator": {"operators": ["MutationTypesEnum.single_add"], "parent_individuals": ["0c821891-a700-488d-b230-e78e10493347"], "type_": "mutation", "uid": "2767ddca-772b-4487-940b-b5ed3c759dd0", "_class_path": "fedot.core.optimisers.opt_history_objects.parent_operator/ParentOperator"}, "uid": "94078775-efc3-44e2-9927-1904df9c9a64", "_class_path": "fedot.core.optimisers.opt_history_objects.individual/Individual"}, {"fitness": {"_values": [0.21498640989582044, 0.2], "_class_path": "fedot.core.optimisers.fitness.fitness/SingleObjFitness"}, "graph": {"operator": {"_nodes": [{"_nodes_from": ["9d8886c4-9356-4764-858e-223c4904f5a6"], "content": {"name": "rf", "params": {"n_jobs": 1, "n_estimators": 100, "criterion": "gini", "max_features": 0.230473113139744, "min_samples_split": 9, "min_samples_leaf": 7, "bootstrap": true}, "metadata": {"metric": null, "_class_path": "fedot.core.pipelines.node/NodeMetadata"}}, "uid": "aac5747d-b303-46e4-b1ba-2c80557bb236", "_class_path": "fedot.core.dag.linked_graph_node/LinkedGraphNode"}, {"_nodes_from": [], "content": {"name": "scaling", "params": {}, "metadata": {"metric": null, "_class_path": "fedot.core.pipelines.node/NodeMetadata"}}, "uid": "9d8886c4-9356-4764-858e-223c4904f5a6", "_class_path": "fedot.core.dag.linked_graph_node/LinkedGraphNode"}], "_postprocess_nodes": {"_class_path": "fedot.core.dag.linked_graph/LinkedGraph._empty_postprocess"}, "_class_path": "fedot.core.dag.linked_graph/LinkedGraph"}, "_class_path": "fedot.core.dag.graph_delegate/GraphDelegate"}, "metadata": {"computation_time_in_seconds": 708.1128995381296, "evaluation_time_iso": "2022-11-02T20:49:53.592981"}, "native_generation": 1, "parent_operator": {"operators": ["<function parameter_change_mutation at 0x7fe423f6b9d0>"], "parent_individuals": ["0c821891-a700-488d-b230-e78e10493347"], "type_": "mutation", "uid": "1f86f87b-1219-497a-ad5c-0ef69e4bcf55", "_class_path": "fedot.core.optimisers.opt_history_objects.parent_operator/ParentOperator"}, "uid": "e008a2c4-f338-468a-b7c4-41fa27df6615", "_class_path": "fedot.core.optimisers.opt_history_objects.individual/Individual"}]}