{"_default_save_dir": "/tmp/FEDOT", "_is_multi_objective": false, "_tuning_result": {"operator": {"_nodes": [{"_nodes_from": ["a92f8317-3423-4e7d-853b-723799eadc68"], "content": {"name": "rf", "params": {"n_jobs": -1, "criterion": "gini", "max_features": 0.1327741000599008, "min_samples_split": 5, "min_samples_leaf": 13, "bootstrap": true}, "metadata": {"metric": null, "_class_path": "fedot.core.pipelines.node/NodeMetadata"}}, "uid": "696e2bd1-c84b-4c6d-beb7-064ac4ffdbeb", "_class_path": "fedot.core.dag.linked_graph_node/LinkedGraphNode"}, {"_nodes_from": [], "content": {"name": "scaling", "params": {}, "metadata": {"metric": null, "_class_path": "fedot.core.pipelines.node/NodeMetadata"}}, "uid": "a92f8317-3423-4e7d-853b-723799eadc68", "_class_path": "fedot.core.dag.linked_graph_node/LinkedGraphNode"}], "_postprocess_nodes": {"_class_path": "fedot.core.dag.linked_graph/LinkedGraph._empty_postprocess"}, "_class_path": "fedot.core.dag.linked_graph/LinkedGraph"}, "_class_path": "fedot.core.dag.graph_delegate/GraphDelegate"}, "archive_history": [["0075da01-cb08-4d82-b6d1-128e072f4d98"], ["7636f62e-b7bc-448a-818f-a1b868896350"], ["7636f62e-b7bc-448a-818f-a1b868896350"]], "individuals": [{"data": ["0075da01-cb08-4d82-b6d1-128e072f4d98"], "generation_num": 0, "label": "initial_assumptions", "metadata": {}, "_class_path": "fedot.core.optimisers.opt_history_objects.generation/Generation"}, {"data": ["7636f62e-b7bc-448a-818f-a1b868896350", "456c472b-6c02-45ad-8bc2-95916b580020", "088e8c06-3779-4e25-b8ec-a7897f12bc57", "0075da01-cb08-4d82-b6d1-128e072f4d98"], "generation_num": 1, "label": "extended_initial_assumptions", "metadata": {}, "_class_path": "fedot.core.optimisers.opt_history_objects.generation/Generation"}, {"data": ["7636f62e-b7bc-448a-818f-a1b868896350"], "generation_num": 2, "label": "final_choices", "metadata": {}, "_class_path": "fedot.core.optimisers.opt_history_objects.generation/Generation"}], "individuals_pool": [{"fitness": {"_values": [-0.7153999999999999, 0.2], "_class_path": "fedot.core.optimisers.fitness.fitness/SingleObjFitness"}, "graph": {"operator": {"_nodes": [{"_nodes_from": ["205a5197-f4c9-4910-9067-523603c94dbe"], "content": {"name": "rf", "params": {"n_jobs": -1}, "metadata": {"metric": null, "_class_path": "fedot.core.pipelines.node/NodeMetadata"}}, "uid": "3383b4af-3c51-4853-aa4c-f54b61613114", "_class_path": "fedot.core.dag.linked_graph_node/LinkedGraphNode"}, {"_nodes_from": [], "content": {"name": "scaling", "params": {}, "metadata": {"metric": null, "_class_path": "fedot.core.pipelines.node/NodeMetadata"}}, "uid": "205a5197-f4c9-4910-9067-523603c94dbe", "_class_path": "fedot.core.dag.linked_graph_node/LinkedGraphNode"}], "_postprocess_nodes": {"_class_path": "fedot.core.dag.linked_graph/LinkedGraph._empty_postprocess"}, "_class_path": "fedot.core.dag.linked_graph/LinkedGraph"}, "_class_path": "fedot.core.dag.graph_delegate/GraphDelegate"}, "metadata": {"computation_time_in_seconds": 1100.5096980449744, "evaluation_time_iso": "2023-01-20T11:34:22.906200", "SA": false}, "native_generation": 0, "parent_operator": null, "uid": "0075da01-cb08-4d82-b6d1-128e072f4d98", "_class_path": "fedot.core.optimisers.opt_history_objects.individual/Individual"}, {"fitness": {"_values": [-0.7462, 0.2], "_class_path": "fedot.core.optimisers.fitness.fitness/SingleObjFitness"}, "graph": {"operator": {"_nodes": [{"_nodes_from": ["52a6535c-4236-4d78-897a-0c8d90e22574"], "content": {"name": "rf", "params": {"n_jobs": -1, "criterion": "gini", "max_features": 0.1327741000599008, "min_samples_split": 5, "min_samples_leaf": 13, "bootstrap": true}, "metadata": {"metric": null, "_class_path": "fedot.core.pipelines.node/NodeMetadata"}}, "uid": "55ce7385-ec4b-4d84-ab8f-535fbf7fd8d0", "_class_path": "fedot.core.dag.linked_graph_node/LinkedGraphNode"}, {"_nodes_from": [], "content": {"name": "scaling", "params": {}, "metadata": {"metric": null, "_class_path": "fedot.core.pipelines.node/NodeMetadata"}}, "uid": "52a6535c-4236-4d78-897a-0c8d90e22574", "_class_path": "fedot.core.dag.linked_graph_node/LinkedGraphNode"}], "_postprocess_nodes": {"_class_path": "fedot.core.dag.linked_graph/LinkedGraph._empty_postprocess"}, "_class_path": "fedot.core.dag.linked_graph/LinkedGraph"}, "_class_path": "fedot.core.dag.graph_delegate/GraphDelegate"}, "metadata": {"computation_time_in_seconds": 2433.024549476104, "evaluation_time_iso": "2023-01-20T12:14:57.454074", "SA": false}, "native_generation": 1, "parent_operator": {"operators": ["<function parameter_change_mutation at 0x7fa2e4ce5b80>"], "parent_individuals": ["0075da01-cb08-4d82-b6d1-128e072f4d98"], "type_": "mutation", "uid": "64d61026-b23a-4f8e-bdfe-bafb285e57ad", "_class_path": "fedot.core.optimisers.opt_history_objects.parent_operator/ParentOperator"}, "uid": "7636f62e-b7bc-448a-818f-a1b868896350", "_class_path": "fedot.core.optimisers.opt_history_objects.individual/Individual"}, {"fitness": {"_values": [-0.7429999999999999, 0.2], "_class_path": "fedot.core.optimisers.fitness.fitness/SingleObjFitness"}, "graph": {"operator": {"_nodes": [{"_nodes_from": ["76b79a56-1e61-44e5-812c-af6dfae4714e"], "content": {"name": "rf", "params": {"n_jobs": -1, "criterion": "gini", "max_features": 0.32265041442911113, "min_samples_split": 8, "min_samples_leaf": 7, "bootstrap": true}, "metadata": {"metric": null, "_class_path": "fedot.core.pipelines.node/NodeMetadata"}}, "uid": "8130a3d9-44ad-4a54-9575-4da0ecc07cd5", "_class_path": "fedot.core.dag.linked_graph_node/LinkedGraphNode"}, {"_nodes_from": [], "content": {"name": "scaling", "params": {}, "metadata": {"metric": null, "_class_path": "fedot.core.pipelines.node/NodeMetadata"}}, "uid": "76b79a56-1e61-44e5-812c-af6dfae4714e", "_class_path": "fedot.core.dag.linked_graph_node/LinkedGraphNode"}], "_postprocess_nodes": {"_class_path": "fedot.core.dag.linked_graph/LinkedGraph._empty_postprocess"}, "_class_path": "fedot.core.dag.linked_graph/LinkedGraph"}, "_class_path": "fedot.core.dag.graph_delegate/GraphDelegate"}, "metadata": {"computation_time_in_seconds": 4393.202962439973, "evaluation_time_iso": "2023-01-20T13:28:10.657134", "SA": false}, "native_generation": 1, "parent_operator": {"operators": ["<function parameter_change_mutation at 0x7fa2e4ce5b80>"], "parent_individuals": ["0075da01-cb08-4d82-b6d1-128e072f4d98"], "type_": "mutation", "uid": "314c7722-548f-4a51-8d6c-d9a5d9a88c3f", "_class_path": "fedot.core.optimisers.opt_history_objects.parent_operator/ParentOperator"}, "uid": "456c472b-6c02-45ad-8bc2-95916b580020", "_class_path": "fedot.core.optimisers.opt_history_objects.individual/Individual"}, {"fitness": {"_values": [-0.6514000000000001, 0.3], "_class_path": "fedot.core.optimisers.fitness.fitness/SingleObjFitness"}, "graph": {"operator": {"_nodes": [{"_nodes_from": ["785c03d2-4c00-4741-8984-8476dd28ba4e"], "content": {"name": "rf", "params": {"n_jobs": -1}, "metadata": {"metric": null, "_class_path": "fedot.core.pipelines.node/NodeMetadata"}}, "uid": "ed201f19-9eb4-4637-84e4-b7f67037f49d", "_class_path": "fedot.core.dag.linked_graph_node/LinkedGraphNode"}, {"_nodes_from": ["200687b7-2f5f-4947-aba4-b69edec3a1cb"], "content": {"name": "scaling", "params": {}, "metadata": {"metric": null, "_class_path": "fedot.core.pipelines.node/NodeMetadata"}}, "uid": "785c03d2-4c00-4741-8984-8476dd28ba4e", "_class_path": "fedot.core.dag.linked_graph_node/LinkedGraphNode"}, {"_nodes_from": [], "content": {"name": "pca", "params": {"svd_solver": "full", "n_components": 0.7}, "metadata": {"metric": null, "_class_path": "fedot.core.pipelines.node/NodeMetadata"}}, "uid": "200687b7-2f5f-4947-aba4-b69edec3a1cb", "_class_path": "fedot.core.dag.linked_graph_node/LinkedGraphNode"}], "_postprocess_nodes": {"_class_path": "fedot.core.dag.linked_graph/LinkedGraph._empty_postprocess"}, "_class_path": "fedot.core.dag.linked_graph/LinkedGraph"}, "_class_path": "fedot.core.dag.graph_delegate/GraphDelegate"}, "metadata": {"computation_time_in_seconds": 767.561487223953, "evaluation_time_iso": "2023-01-20T13:40:58.218711", "SA": false}, "native_generation": 1, "parent_operator": {"operators": ["MutationTypesEnum.single_add", "MutationTypesEnum.single_add", "MutationTypesEnum.single_add", "MutationTypesEnum.single_add"], "parent_individuals": ["0075da01-cb08-4d82-b6d1-128e072f4d98"], "type_": "mutation", "uid": "d41a3cba-9cf2-405a-9576-960d295f5ce3", "_class_path": "fedot.core.optimisers.opt_history_objects.parent_operator/ParentOperator"}, "uid": "088e8c06-3779-4e25-b8ec-a7897f12bc57", "_class_path": "fedot.core.optimisers.opt_history_objects.individual/Individual"}], "_class_path": "fedot.core.optimisers.opt_history_objects.opt_history/OptHistory"}